{"id":"D_kwDONzrbkM4Alwvc","title":"Test Post - Hello World","body":"This is a test post to verify the publish-to-discussions workflow.\n## Features to Test\n- Creating a new discussion from a local markdown file\n- Correctly generating the file path with `number` and `id`\n- Updating the README.md table of contents\n- Committing all generated files back to the repo\n## Content\nLorem ipsum dolor sit amet, consectetur adipiscing elit. Sed do eiusmod tempor incididunt ut labore et dolore magna aliqua.\n### Code Block\n```bash\necho \"If you see this in the discussion body, the publish worked!\"\n```\n> This is a blockquote to test markdown rendering.\n**Last updated**: 2026-04-17","number":43,"labels":{"nodes":[]},"category":{"id":"DIC_kwDONzrbkM4Cmnbf","name":"Show and tell","slug":"show-and-tell","emoji":":raised_hands:","emojiHTML":"<div>🙌</div>"},"author":{"login":"onnttf"},"authorAssociation":"OWNER","createdAt":"2026-04-17T05:13:45Z","updatedAt":"2026-04-17T05:13:45Z","repository":{"id":"R_kgDONzrbkA","url":"https://github.com/onnttf/blog"},"url":"https://github.com/onnttf/blog/discussions/43","jsonFilePath":"discussions/43-D_kwDONzrbkM4Alwvc.json","markdownFilePath":"2026/04/43-D_kwDONzrbkM4Alwvc.md"}
